databricks_dq_module-1.2.5.dist-info/licenses/LICENSE
dq_module/__init__.py
dq_module/dq.py
databricks_dq_module-1.2.5.dist-info/METADATA
databricks_dq_module-1.2.5.dist-info/WHEEL
databricks_dq_module-1.2.5.dist-info/top_level.txt
databricks_dq_module-1.2.5.dist-info/RECORD
