Metadata-Version: 2.4
Name: databricks-dq-module
Version: 1.2.5
Summary: Data quality checker for Databricks pipelines
Author: Noah Kim
Author-email: noah24.kim@gmail.com
Classifier: Programming Language :: Python :: 3
Classifier: License :: OSI Approved :: MIT License
Requires-Python: >= 3.6
License-File: LICENSE
Dynamic: author
Dynamic: author-email
Dynamic: classifier
Dynamic: license-file
Dynamic: requires-python
Dynamic: summary
